odoo/addons/hr_employee_calendar_planning/README.rst
odoo/addons/hr_employee_calendar_planning/__init__.py
odoo/addons/hr_employee_calendar_planning/__manifest__.py
odoo/addons/hr_employee_calendar_planning/hooks.py
odoo/addons/hr_employee_calendar_planning/i18n/ca.po
odoo/addons/hr_employee_calendar_planning/i18n/ca_ES.po
odoo/addons/hr_employee_calendar_planning/i18n/de.po
odoo/addons/hr_employee_calendar_planning/i18n/es.po
odoo/addons/hr_employee_calendar_planning/i18n/es_AR.po
odoo/addons/hr_employee_calendar_planning/i18n/fr.po
odoo/addons/hr_employee_calendar_planning/i18n/hr_employee_calendar_planning.pot
odoo/addons/hr_employee_calendar_planning/i18n/it.po
odoo/addons/hr_employee_calendar_planning/migrations/14.0.1.2.0/post-migration.py
odoo/addons/hr_employee_calendar_planning/migrations/14.0.1.3.0/post-migration.py
odoo/addons/hr_employee_calendar_planning/models/__init__.py
odoo/addons/hr_employee_calendar_planning/models/hr_employee.py
odoo/addons/hr_employee_calendar_planning/models/resource_calendar.py
odoo/addons/hr_employee_calendar_planning/readme/CONFIGURE.rst
odoo/addons/hr_employee_calendar_planning/readme/CONTRIBUTORS.rst
odoo/addons/hr_employee_calendar_planning/readme/DESCRIPTION.rst
odoo/addons/hr_employee_calendar_planning/readme/INSTALL.rst
odoo/addons/hr_employee_calendar_planning/readme/ROADMAP.rst
odoo/addons/hr_employee_calendar_planning/security/ir.model.access.csv
odoo/addons/hr_employee_calendar_planning/static/description/icon.png
odoo/addons/hr_employee_calendar_planning/static/description/index.html
odoo/addons/hr_employee_calendar_planning/tests/__init__.py
odoo/addons/hr_employee_calendar_planning/tests/test_hr_employee_calendar_planning.py
odoo/addons/hr_employee_calendar_planning/views/hr_employee_views.xml
odoo/addons/hr_employee_calendar_planning/views/resource_calendar_views.xml
odoo14_addon_hr_employee_calendar_planning-14.0.1.6.1.dist-info/METADATA
odoo14_addon_hr_employee_calendar_planning-14.0.1.6.1.dist-info/WHEEL
odoo14_addon_hr_employee_calendar_planning-14.0.1.6.1.dist-info/top_level.txt
odoo14_addon_hr_employee_calendar_planning-14.0.1.6.1.dist-info/RECORD
